deliverfresh_whatsapp_order/__init__.py
deliverfresh_whatsapp_order/clean.py
deliverfresh_whatsapp_order-0.1.9.dist-info/licenses/LICENSE
deliverfresh_whatsapp_order-0.1.9.dist-info/METADATA
deliverfresh_whatsapp_order-0.1.9.dist-info/WHEEL
deliverfresh_whatsapp_order-0.1.9.dist-info/top_level.txt
deliverfresh_whatsapp_order-0.1.9.dist-info/RECORD
