Metadata-Version: 2.4
Name: deliverfresh-whatsapp-order
Version: 0.1.9
Summary: Clean and normalize WhatsApp chat orders into structured product lists.
Author-email: Raman Perumal <rperumal3000@gmail.com>
License: MIT License
Requires-Python: >=3.7
License-File: LICENSE
Provides-Extra: dev
Requires-Dist: pytest; extra == "dev"
Requires-Dist: pytest-cov; extra == "dev"
Requires-Dist: build; extra == "dev"
Requires-Dist: twine; extra == "dev"
Dynamic: license-file
